deltat/__init__.py
deltat-1.1.2.dist-info/LICENSE.md
deltat-1.1.2.dist-info/METADATA
deltat-1.1.2.dist-info/WHEEL
deltat-1.1.2.dist-info/top_level.txt
deltat-1.1.2.dist-info/RECORD
