Metadata-Version: 2.1
Name: deltat
Version: 1.1.2
Summary: Friendly text to timedelta conversion
Home-page: https://gitlab.com/MarcelWaldvogel/deltat
Author: Marcel Waldvogel
Author-email: marcel.waldvogel@trifence.ch
License: MIT
Project-URL: Source, https://gitlab.com/MarcelWaldvogel/deltat
Project-URL: Source Code, https://github.com/MarcelWaldvogel/deltat
Platform: UNKNOWN
Classifier: Development Status :: 5 - Production/Stable
Classifier: Intended Audience :: Information Technology
Classifier: Programming Language :: Python
Classifier: License :: OSI Approved :: MIT License
Classifier: Operating System :: OS Independent
Classifier: Natural Language :: English
Requires-Python: >=3.2
License-File: LICENSE.md
